{
  "collectionName": "components_layout_split_columns",
  "info": {
    "displayName": "Split Column",
    "icon": "grid",
    "description": ""
  },
  "options": {},
  "attributes": {
    "description": {
      "type": "customField",
      "options": {
        "preset": "custom"
      },
      "customField": "plugin::ckeditor5.CKEditor",
      "required": true
    },
    "media": {
      "type": "media",
      "multiple": false,
      "required": true,
      "allowedTypes": [
        "images",
        "videos"
      ]
    },
    "mediaAlignment": {
      "type": "enumeration",
      "enum": [
        "left",
        "right"
      ],
      "default": "right",
      "required": true
    },
    "button": {
      "displayName": "Button",
      "type": "component",
      "repeatable": false,
      "component": "interactions.button"
    }
  }
}
